streamlit_rjsf/__init__.py
streamlit_rjsf/build/assets/index-470959c6.js
streamlit_rjsf/build/favicon.ico
streamlit_rjsf/build/index.html
streamlit_rjsf/build/logo192.png
streamlit_rjsf/build/logo512.png
streamlit_rjsf/build/manifest.json
streamlit_rjsf/build/robots.txt
streamlit_rjsf-0.1.0.dist-info/LICENSE
streamlit_rjsf-0.1.0.dist-info/METADATA
streamlit_rjsf-0.1.0.dist-info/WHEEL
streamlit_rjsf-0.1.0.dist-info/RECORD
